twofer/__init__.py
twofer/model.py
twofer/client/cli.py
twofer/client/config.py
twofer/helper/functools.py
twofer/server/config.py
twofer/server/flaskapp.py
twofer/server/api/__init__.py
twofer/server/api/tweepyimpl.py
twofer/server/data/templates/callback.html
twofer/server/data/templates/index.html
twofer/server/database/__init__.py
twofer/server/database/jsonimpl.py
twofer-0.3.1.1.dist-info/LICENSE
twofer-0.3.1.1.dist-info/METADATA
twofer-0.3.1.1.dist-info/WHEEL
twofer-0.3.1.1.dist-info/entry_points.txt
twofer-0.3.1.1.dist-info/top_level.txt
twofer-0.3.1.1.dist-info/RECORD
