Metadata-Version: 2.1
Name: twofer
Version: 0.3.1.1
Summary: Twofer is a 'tweet transfer agent' server / client.
Home-page: https://bitbucket.org/emptypage/twofer/
Author: Masaaki Shibata
Author-email: mshibata@emptypage.jp
License: MIT
Keywords: twitter
Classifier: Programming Language :: Python :: 3.11
Classifier: Programming Language :: Python :: 3.10
Classifier: License :: OSI Approved :: MIT License
Classifier: Operating System :: OS Independent
License-File: LICENSE
Requires-Dist: appdirs
Requires-Dist: flask
Requires-Dist: python-dotenv
Requires-Dist: tweepy
